up_siadex/__init__.py
up_siadex/dt_parser.py
up_siadex/siadex_planner.py
up_siadex/bin/planner
up_siadex-0.0.1.dist-info/METADATA
up_siadex-0.0.1.dist-info/WHEEL
up_siadex-0.0.1.dist-info/top_level.txt
up_siadex-0.0.1.dist-info/RECORD
