Metadata-Version: 2.1
Name: up-siadex
Version: 0.0.1
Summary: up_siadex
Home-page: https://github.com/UGR-IntelligentSystemsGroup/up-siadex
Author: UGR Intelligent Systems Group
Author-email: jorgesoler@ugr.es,ignaciovellido@ugr.es
License: APACHE
